finiteautomata/__init__.py
finiteautomata/core.py
finiteautomata/renderer.py
finiteautomata-1.2.0.dist-info/METADATA
finiteautomata-1.2.0.dist-info/WHEEL
finiteautomata-1.2.0.dist-info/top_level.txt
finiteautomata-1.2.0.dist-info/RECORD
