Metadata-Version: 2.2
Name: finiteautomata
Version: 1.2.0
Summary: A more intuitive way to create finite automata diagrams.
Home-page: https://github.com/vishruthb/finiteautomata
Author: Vishruth Bharath
Author-email: 
Classifier: Programming Language :: Python :: 3
Classifier: License :: OSI Approved :: MIT License
Classifier: Operating System :: OS Independent
Requires-Python: >=3.6
Provides-Extra: cairo
Requires-Dist: cairosvg>=2.7; extra == "cairo"
Provides-Extra: dev
Requires-Dist: pytest>=7.0; extra == "dev"
Requires-Dist: pytest-cov>=4.0; extra == "dev"
Requires-Dist: cairosvg>=2.7; extra == "dev"
Dynamic: author
Dynamic: classifier
Dynamic: description
Dynamic: description-content-type
Dynamic: home-page
Dynamic: provides-extra
Dynamic: requires-python
Dynamic: summary
